certbot_plugin_websupport/__init__.py
certbot_plugin_websupport/dns.py
certbot_plugin_websupport/dns_test.py
certbot_plugin_websupport-0.2.0.dist-info/LICENCE
certbot_plugin_websupport-0.2.0.dist-info/METADATA
certbot_plugin_websupport-0.2.0.dist-info/WHEEL
certbot_plugin_websupport-0.2.0.dist-info/entry_points.txt
certbot_plugin_websupport-0.2.0.dist-info/top_level.txt
certbot_plugin_websupport-0.2.0.dist-info/RECORD
