Metadata-Version: 2.1
Name: certbot-plugin-websupport
Version: 0.2.0
Summary: Websupport DNS Authenticator plugin for Certbot
Home-page: https://github.com/Mordred/certbot-plugin-websupport
Author: Martin Jantosovic
Author-email: jantosovic.martin@gmail.com
License: MIT
Classifier: Development Status :: 3 - Alpha
Classifier: Environment :: Plugins
Classifier: Intended Audience :: System Administrators
Classifier: License :: OSI Approved :: MIT License
Classifier: Operating System :: POSIX :: Linux
Classifier: Programming Language :: Python
Classifier: Programming Language :: Python :: 2
Classifier: Programming Language :: Python :: 2.7
Classifier: Programming Language :: Python :: 3
Classifier: Programming Language :: Python :: 3.4
Classifier: Programming Language :: Python :: 3.5
Classifier: Programming Language :: Python :: 3.6
Classifier: Programming Language :: Python :: 3.7
Classifier: Programming Language :: Python :: 3.8
Classifier: Programming Language :: Python :: 3.9
Classifier: Programming Language :: Python :: 3.10
Classifier: Programming Language :: Python :: 3.11
Classifier: Programming Language :: Python :: 3.12
Classifier: Topic :: Internet :: WWW/HTTP
Classifier: Topic :: Security
Classifier: Topic :: System :: Installation/Setup
Classifier: Topic :: System :: Networking
Classifier: Topic :: System :: Systems Administration
Classifier: Topic :: Utilities
Requires-Python: >=2.7, !=3.0.*, !=3.1.*, !=3.2.*, !=3.3.*
License-File: LICENCE
Requires-Dist: certbot>=0.38.0
Requires-Dist: requests
Requires-Dist: setuptools
Requires-Dist: zope.interface
Provides-Extra: docs
Requires-Dist: Sphinx>=1.0; extra == "docs"
Requires-Dist: sphinx-rtd-theme; extra == "docs"
